.flake8
CHANGELOG.rst
CONTRIBUTING.rst
LICENSE
MANIFEST.in
README.rst
SUPPORT.rst
pyproject.toml
setup.py
docs/FAQ.rst
docs/Makefile
docs/advanced_installation.rst
docs/bibliography.rst
docs/conf.py
docs/contributing.rst
docs/history_output_logging.rst
docs/index.rst
docs/introduction.rst
docs/introduction_latex.rst
docs/known_issues.rst
docs/latex_index.rst
docs/libe_module.rst
docs/nitpicky
docs/overview_usecases.rst
docs/posters.rst
docs/programming_libE.rst
docs/references.bib
docs/release_notes.rst
docs/requirements.txt
docs/rst_formatting_guidelines
docs/running_libE.rst
docs/spelling_wordlist.txt
docs/utilities.rst
docs/welcome.rst
docs/xSDK_policy_compatibility.md
docs/_static/my_theme.css
docs/data_structures/alloc_specs.rst
docs/data_structures/data_structures.rst
docs/data_structures/exit_criteria.rst
docs/data_structures/gen_specs.rst
docs/data_structures/libE_specs.rst
docs/data_structures/persis_info.rst
docs/data_structures/platform_specs.rst
docs/data_structures/sim_specs.rst
docs/dev_guide/dev_API/developer_API.rst
docs/dev_guide/dev_API/env_resources_module.rst
docs/dev_guide/dev_API/history_module.rst
docs/dev_guide/dev_API/manager_module.rst
docs/dev_guide/dev_API/mpi_resources_module.rst
docs/dev_guide/dev_API/node_resources_module.rst
docs/dev_guide/dev_API/resources_module.rst
docs/dev_guide/dev_API/rset_resources_module.rst
docs/dev_guide/dev_API/scheduler_module.rst
docs/dev_guide/dev_API/worker_module.rst
docs/dev_guide/dev_API/worker_resources_module.rst
docs/dev_guide/release_management/release_index.rst
docs/dev_guide/release_management/release_process.rst
docs/dev_guide/release_management/release_platforms/index.rst
docs/dev_guide/release_management/release_platforms/rel_conda.rst
docs/dev_guide/release_management/release_platforms/rel_github.rst
docs/dev_guide/release_management/release_platforms/rel_pypi.rst
docs/dev_guide/release_management/release_platforms/rel_spack.rst
docs/examples/alloc_funcs.rst
docs/examples/aposmm.rst
libensemble.egg-info/PKG-INFO
libensemble.egg-info/SOURCES.txt
libensemble.egg-info/dependency_links.txt
libensemble.egg-info/requires.txt
libensemble.egg-info/top_level.txt
