Metadata-Version: 2.1
Name: libensemble
Version: 1.5.0
Summary: A Python toolkit for coordinating asynchronous and dynamic ensembles of calculations.
Author: Jeffrey Larson, Stephen Hudson, Stefan M. Wild, David Bindel, John-Luke Navarro
License: BSD 3-Clause License
Project-URL: Documentation, https://libensemble.readthedocs.io/en/main/
Project-URL: Repository, https://github.com/Libensemble/libensemble
Project-URL: Issues, https://github.com/Libensemble/libensemble/issues
Classifier: Development Status :: 5 - Production/Stable
Classifier: Intended Audience :: Developers
Classifier: Intended Audience :: Science/Research
Classifier: License :: OSI Approved :: BSD License
Classifier: Natural Language :: English
Classifier: Operating System :: POSIX :: Linux
Classifier: Operating System :: Unix
Classifier: Operating System :: MacOS
Classifier: Programming Language :: Python :: 3
Classifier: Programming Language :: Python :: 3.10
Classifier: Programming Language :: Python :: 3.11
Classifier: Programming Language :: Python :: 3.12
Classifier: Programming Language :: Python :: 3.13
Classifier: Programming Language :: Python :: Implementation :: CPython
Classifier: Topic :: Scientific/Engineering
Classifier: Topic :: Software Development :: Libraries :: Python Modules
Requires-Python: >=3.10
License-File: LICENSE
Requires-Dist: numpy
Requires-Dist: psutil
Requires-Dist: pydantic
Requires-Dist: pyyaml
Requires-Dist: tomli
